MANIFEST.in
README.txt
setup.cfg
setup.py
tw2/__init__.py
tw2.dyntext.egg-info/PKG-INFO
tw2.dyntext.egg-info/SOURCES.txt
tw2.dyntext.egg-info/dependency_links.txt
tw2.dyntext.egg-info/entry_points.txt
tw2.dyntext.egg-info/namespace_packages.txt
tw2.dyntext.egg-info/not-zip-safe
tw2.dyntext.egg-info/requires.txt
tw2.dyntext.egg-info/top_level.txt
tw2/dyntext/__init__.py
tw2/dyntext/samples.py
tw2/dyntext/widgets.py
tw2/dyntext/static/dyntext.js
tw2/dyntext/templates/__init__.py
tw2/dyntext/templates/__init__.pyc
tw2/dyntext/templates/dyntext.mak