Metadata-Version: 1.0
Name: tw2.dyntext
Version: 0.0.5
Summary: Dynamic Text widget for TW2. Allows text to be pulled from JSON objects live.
Home-page: http://github.com/toscawidgets/tw2.dyntext
Author: Greg Jurman
Author-email: gdj2214@rit.edu
License: UNKNOWN
Keywords: toscawidgets.widgets
Platform: UNKNOWN
Classifier: Development Status :: 3 - Alpha
Classifier: Environment :: Web Environment
Classifier: Environment :: Web Environment :: ToscaWidgets
Classifier: Topic :: Software Development :: Libraries :: Python Modules
Classifier: Topic :: Software Development :: Widget Sets
Classifier: Intended Audience :: Developers
Classifier: Operating System :: OS Independent
Classifier: Programming Language :: Python
